setup.py
email142857.egg-info/PKG-INFO
email142857.egg-info/SOURCES.txt
email142857.egg-info/dependency_links.txt
email142857.egg-info/top_level.txt
ljf7/__init__.py
ljf7/email.py
ljf7/fib.py