Metadata-Version: 2.1
Name: email142857
Version: 10
Summary: To solve fib by recursion
Author: Linus Trovalds
